{
  "示例配置说明": "键为关键词（包含冒号），值为可选的定位与样式覆盖。业务中也可完全由输入数据提供，仅作示例。",
  "身份证号：": {
    "offset_x": 2,
    "offset_y": 2,
    "max_width": 180,
    "line_spacing": 14
  },
  "企业名称：": {
    "offset_x": 2,
    "offset_y": 2,
    "max_width": 220,
    "line_spacing": 14
  }
}


{
  "示例配置说明": "键为关键词（包含冒号），值为可选的定位与样式覆盖。业务中也可完全由输入数据提供，仅作示例。",
  "身份证号：": {
    "offset_x": 2,
    "offset_y": 2,
    "max_width": 180,
    "line_spacing": 14
  },
  "企业名称：": {
    "offset_x": 2,
    "offset_y": 2,
    "max_width": 220,
    "line_spacing": 14
  }
}


